setup.py
KR580/__init__.py
KR580/__main__.py
KR580/memory_model.py
KR580.egg-info/PKG-INFO
KR580.egg-info/SOURCES.txt
KR580.egg-info/dependency_links.txt
KR580.egg-info/entry_points.txt
KR580.egg-info/requires.txt
KR580.egg-info/top_level.txt
KR580/compiler/__init__.py
KR580/compiler/compiler.py
KR580/compiler/compiler_utils.py
KR580/compiler/lexer.py
KR580/compiler/opcodes.py
KR580/compiler/parsetab.py
KR580/compiler/symbols.py
KR580/emulator/CPU.so
KR580/emulator/__init__.py
KR580/emulator/emulator.py
KR580/gui/__init__.py
KR580/gui/base_form.py
KR580/gui/mainForm.py
KR580/gui/numlabel.py
KR580/gui/regname.py