Metadata-Version: 1.1
Name: KR580
Version: 0.0.1
Summary: KR580 educational emulator.
Home-page: https://github.com/gsedometov/KR580-emulator
Author: Georgii Sedometov
Author-email: gs@sedometov.com
License: MIT
Keywords: KR580 emulator assembler education
Platform: UNKNOWN
Classifier: Development Status :: 3 - Alpha
Classifier: Intended Audience :: Education
Classifier: License :: OSI Approved :: MIT License
Classifier: Programming Language :: Python :: 3
